wordmaze/__init__.py
wordmaze/wordmaze.py
wordmaze/utils/__init__.py
wordmaze/utils/dataclasses.py
wordmaze/utils/sequences.py
wordmaze-0.3.6.dist-info/LICENSE
wordmaze-0.3.6.dist-info/METADATA
wordmaze-0.3.6.dist-info/WHEEL
wordmaze-0.3.6.dist-info/top_level.txt
wordmaze-0.3.6.dist-info/RECORD
