Metadata-Version: 2.1
Name: wordmaze
Version: 0.3.6
Summary: Words and textboxes made amazing
Home-page: https://github.com/elint-tech/wordmaze/
Author: elint-tech
Author-email: contato@elint.com.br
License: MIT
Download-URL: https://github.com/elint-tech/wordmaze/dist/wordmaze-0.3.6.tar.gz
Keywords: wordmaze,ocr,pdf,word,words,text,textbox,textboxes,text-mining,text-mining-analysis
Platform: UNKNOWN
Classifier: Development Status :: 4 - Beta
Classifier: License :: OSI Approved :: MIT License
Classifier: Intended Audience :: Developers
Classifier: Topic :: Software Development
Classifier: Topic :: Utilities
Classifier: Programming Language :: Python :: 3
Classifier: Programming Language :: Python :: 3.7
Classifier: Programming Language :: Python :: 3.8
Classifier: Operating System :: OS Independent
Requires-Dist: dataclassy (>=0.8)
Requires-Dist: funcy (>=1.15)
